extended_memory_mcp/__init__.py
extended_memory_mcp/server.py
extended_memory_mcp/config/__init__.py
extended_memory_mcp/config/tools/__init__.py
extended_memory_mcp/config/tools/descriptions_loader.py
extended_memory_mcp/config/tools/descriptions/forget_context.md
extended_memory_mcp/config/tools/descriptions/get_popular_tags.md
extended_memory_mcp/config/tools/descriptions/list_all_projects.md
extended_memory_mcp/config/tools/descriptions/load_contexts.md
extended_memory_mcp/config/tools/descriptions/save_context.md
extended_memory_mcp/config/tools/schema/input_schemas.json
extended_memory_mcp/core/__init__.py
extended_memory_mcp/core/config_utils.py
extended_memory_mcp/core/errors.py
extended_memory_mcp/core/instruction_engine.py
extended_memory_mcp/core/instruction_manager.py
extended_memory_mcp/core/project_utils.py
extended_memory_mcp/core/config/__init__.py
extended_memory_mcp/core/config/config_loader.py
extended_memory_mcp/core/memory/__init__.py
extended_memory_mcp/core/memory/context_repository.py
extended_memory_mcp/core/memory/database_manager.py
extended_memory_mcp/core/memory/instruction_service.py
extended_memory_mcp/core/memory/memory_facade.py
extended_memory_mcp/core/memory/tags_repository.py
extended_memory_mcp/core/memory/services/__init__.py
extended_memory_mcp/core/memory/services/analytics_service.py
extended_memory_mcp/core/memory/services/context_service.py
extended_memory_mcp/core/storage/__init__.py
extended_memory_mcp/core/storage/connection_parser.py
extended_memory_mcp/core/storage/storage_factory.py
extended_memory_mcp/core/storage/interfaces/__init__.py
extended_memory_mcp/core/storage/interfaces/storage_provider.py
extended_memory_mcp/core/storage/providers/__init__.py
extended_memory_mcp/core/storage/providers/redis/__init__.py
extended_memory_mcp/core/storage/providers/redis/redis_provider.py
extended_memory_mcp/core/storage/providers/redis/services/__init__.py
extended_memory_mcp-0.9.0.dist-info/licenses/LICENSE
extended_memory_mcp-0.9.0.dist-info/METADATA
extended_memory_mcp-0.9.0.dist-info/WHEEL
extended_memory_mcp-0.9.0.dist-info/entry_points.txt
extended_memory_mcp-0.9.0.dist-info/top_level.txt
extended_memory_mcp-0.9.0.dist-info/RECORD
