Metadata-Version: 2.4
Name: extended-memory-mcp
Version: 0.9.0
Summary: Model Context Protocol server for AI memory and context preservation
Author: Sergey Smirnov
Classifier: Development Status :: 4 - Beta
Classifier: Intended Audience :: Developers
Classifier: License :: OSI Approved :: MIT License
Classifier: Programming Language :: Python :: 3
Classifier: Programming Language :: Python :: 3.8
Classifier: Programming Language :: Python :: 3.9
Classifier: Programming Language :: Python :: 3.10
Classifier: Programming Language :: Python :: 3.11
Classifier: Programming Language :: Python :: 3.12
Requires-Python: >=3.8,<4.0
License-File: LICENSE
Requires-Dist: aiosqlite>=0.19.0
Requires-Dist: pyyaml>=6.0.0
Requires-Dist: jinja2>=3.1.0
Requires-Dist: platformdirs>=3.0.0
Provides-Extra: redis
Requires-Dist: redis[hiredis]>=4.5.0; extra == "redis"
Provides-Extra: dev
Requires-Dist: pytest>=7.4.0; extra == "dev"
Requires-Dist: pytest-asyncio>=0.21.0; extra == "dev"
Requires-Dist: pytest-cov>=4.0.0; extra == "dev"
Dynamic: author
Dynamic: classifier
Dynamic: license-file
Dynamic: provides-extra
Dynamic: requires-dist
Dynamic: requires-python
Dynamic: summary
